{"name":"Donut shop","tagline":"","body":"# donut_shop\r\nThis is a class project for Codefellows B-33. Images are only used for educational purposes.\r\n\r\nThe focus of this site is on a randomly generated table that is created with Javascript to predict the amount of donuts that Top Pot will need every hour, for each of their locations.\r\nThe input field allows a user to add an additional location to the table by submitting a new location, minimum and maximum customers, and an average donuts per cutsomer.\r\n\r\nImage Sources\r\nDog and donuts: https://twitter.com/marniethedog/status/474941351923310592\r\n\r\n\r\n\r\nSprinkle donut: https://www.stickermule.com/marketplace/4224-cute-pink-retro-sprinkles-doughnut\r\n\r\n\r\nColor inspiration from this Dribbble shot by Fabricio Rosa Marques https://dribbble.com/shots/2193921-Darth-Rider\r\n\r\nDonut animation inspired by http://codepen.io/valhead/pen/rfump\r\n","google":"","note":"Don't delete this file! It's used internally to help with page regeneration."}